linreg/__init__.py
linreg/linreg.py
linreg-0.1.2.dist-info/LICENSE
linreg-0.1.2.dist-info/METADATA
linreg-0.1.2.dist-info/WHEEL
linreg-0.1.2.dist-info/top_level.txt
linreg-0.1.2.dist-info/RECORD
