Metadata-Version: 2.1
Name: linreg
Version: 0.1.2
Summary: Simple and flexible interface for basic linear regression
Home-page: https://github.com/purpleladydragons/linreg
Author: Austin Steady
Author-email: asteady23@gmail.com
Project-URL: Bug Tracker, https://github.com/purpleladydragons/linreg/issues
Classifier: Programming Language :: Python :: 3
Classifier: License :: OSI Approved :: MIT License
Classifier: Operating System :: OS Independent
Requires-Python: >=3.6
License-File: LICENSE
Requires-Dist: scikit-learn (==1.1.0)
Requires-Dist: matplotlib (==3.5.2)
Requires-Dist: numpy (==1.22.3)
